{
  "config": {
    "argv": [
      "C:\\Program Files\\nodejs\\node.exe",
      "D:\\falabella\\node_modules\\@playwright\\test\\cli.js",
      "test"
    ],
    "configFile": "D:\\falabella\\playwright.config.ts",
    "rootDir": "D:/falabella/tests/e2e",
    "failOnFlakyTests": false,
    "forbidOnly": false,
    "fullyParallel": true,
    "globalSetup": null,
    "globalTeardown": null,
    "globalTimeout": 0,
    "grep": {},
    "grepInvert": null,
    "maxFailures": 0,
    "metadata": {
      "actualWorkers": 4
    },
    "preserveOutput": "always",
    "projects": [
      {
        "outputDir": "D:/falabella/test-results",
        "repeatEach": 1,
        "retries": 1,
        "metadata": {
          "actualWorkers": 4
        },
        "id": "chromium",
        "name": "chromium",
        "testDir": "D:/falabella/tests/e2e",
        "testIgnore": [],
        "testMatch": [
          "**/*.@(spec|test).?(c|m)[jt]s?(x)"
        ],
        "timeout": 30000
      }
    ],
    "quiet": false,
    "reporter": [
      [
        "list",
        null
      ],
      [
        "html",
        {
          "outputFile": "docs/html-report",
          "open": "never"
        }
      ],
      [
        "json",
        {
          "outputFile": "docs/json-report.json"
        }
      ]
    ],
    "reportSlowTests": {
      "max": 5,
      "threshold": 300000
    },
    "shard": null,
    "tags": [],
    "updateSnapshots": "missing",
    "updateSourceMethod": "patch",
    "version": "1.61.1",
    "workers": 4,
    "webServer": null
  },
  "suites": [
    {
      "title": "falabella_playwright.spec.ts",
      "file": "falabella_playwright.spec.ts",
      "column": 0,
      "line": 0,
      "specs": [],
      "suites": [
        {
          "title": "Suite de Pruebas E2E - SGI Falabella (Búsqueda y Carrito)",
          "file": "falabella_playwright.spec.ts",
          "line": 2,
          "column": 6,
          "specs": [
            {
              "title": "TC-01: Búsqueda Exitosa - Coincidencia de texto para Smart TV",
              "ok": false,
              "tags": [],
              "tests": [
                {
                  "timeout": 30000,
                  "annotations": [],
                  "expectedStatus": "passed",
                  "projectId": "chromium",
                  "projectName": "chromium",
                  "results": [
                    {
                      "workerIndex": 0,
                      "parallelIndex": 0,
                      "status": "timedOut",
                      "duration": 37782,
                      "error": {
                        "message": "\u001b[31mTest timeout of 30000ms exceeded.\u001b[39m",
                        "stack": "\u001b[31mTest timeout of 30000ms exceeded.\u001b[39m"
                      },
                      "errors": [
                        {
                          "message": "\u001b[31mTest timeout of 30000ms exceeded.\u001b[39m"
                        }
                      ],
                      "stdout": [],
                      "stderr": [],
                      "retry": 0,
                      "startTime": "2026-07-14T01:48:02.745Z",
                      "annotations": [],
                      "attachments": [
                        {
                          "name": "screenshot",
                          "contentType": "image/png",
                          "path": "D:\\falabella\\test-results\\falabella_playwright-Suite-24d31-ncia-de-texto-para-Smart-TV-chromium\\test-failed-1.png"
                        },
                        {
                          "name": "video",
                          "contentType": "video/webm",
                          "path": "D:\\falabella\\test-results\\falabella_playwright-Suite-24d31-ncia-de-texto-para-Smart-TV-chromium\\video.webm"
                        },
                        {
                          "name": "error-context",
                          "contentType": "text/markdown",
                          "path": "D:\\falabella\\test-results\\falabella_playwright-Suite-24d31-ncia-de-texto-para-Smart-TV-chromium\\error-context.md"
                        }
                      ]
                    },
                    {
                      "workerIndex": 4,
                      "parallelIndex": 0,
                      "status": "timedOut",
                      "duration": 45105,
                      "error": {
                        "message": "\u001b[31mTest timeout of 30000ms exceeded.\u001b[39m",
                        "stack": "\u001b[31mTest timeout of 30000ms exceeded.\u001b[39m"
                      },
                      "errors": [
                        {
                          "message": "\u001b[31mTest timeout of 30000ms exceeded.\u001b[39m"
                        }
                      ],
                      "stdout": [],
                      "stderr": [],
                      "retry": 1,
                      "startTime": "2026-07-14T01:48:48.803Z",
                      "annotations": [],
                      "attachments": [
                        {
                          "name": "screenshot",
                          "contentType": "image/png",
                          "path": "D:\\falabella\\test-results\\falabella_playwright-Suite-24d31-ncia-de-texto-para-Smart-TV-chromium-retry1\\test-failed-1.png"
                        },
                        {
                          "name": "video",
                          "contentType": "video/webm",
                          "path": "D:\\falabella\\test-results\\falabella_playwright-Suite-24d31-ncia-de-texto-para-Smart-TV-chromium-retry1\\video.webm"
                        },
                        {
                          "name": "error-context",
                          "contentType": "text/markdown",
                          "path": "D:\\falabella\\test-results\\falabella_playwright-Suite-24d31-ncia-de-texto-para-Smart-TV-chromium-retry1\\error-context.md"
                        },
                        {
                          "name": "trace",
                          "contentType": "application/zip",
                          "path": "D:\\falabella\\test-results\\falabella_playwright-Suite-24d31-ncia-de-texto-para-Smart-TV-chromium-retry1\\trace.zip"
                        }
                      ]
                    }
                  ],
                  "status": "unexpected"
                }
              ],
              "id": "784c2edf0f252052d463-5d1694f21699313276d7",
              "file": "falabella_playwright.spec.ts",
              "line": 7,
              "column": 7
            },
            {
              "title": "TC-02: Búsqueda de Robustez - Sanitización de scripts maliciosos",
              "ok": true,
              "tags": [],
              "tests": [
                {
                  "timeout": 30000,
                  "annotations": [],
                  "expectedStatus": "passed",
                  "projectId": "chromium",
                  "projectName": "chromium",
                  "results": [
                    {
                      "workerIndex": 1,
                      "parallelIndex": 1,
                      "status": "passed",
                      "duration": 16788,
                      "errors": [],
                      "stdout": [],
                      "stderr": [],
                      "retry": 0,
                      "startTime": "2026-07-14T01:48:02.779Z",
                      "annotations": [],
                      "attachments": []
                    }
                  ],
                  "status": "expected"
                }
              ],
              "id": "784c2edf0f252052d463-a76537c344fbd8e67816",
              "file": "falabella_playwright.spec.ts",
              "line": 33,
              "column": 7
            },
            {
              "title": "TC-03: Filtros Avanzados - Selección de faceta por rango de precios",
              "ok": true,
              "tags": [],
              "tests": [
                {
                  "timeout": 30000,
                  "annotations": [],
                  "expectedStatus": "passed",
                  "projectId": "chromium",
                  "projectName": "chromium",
                  "results": [
                    {
                      "workerIndex": 2,
                      "parallelIndex": 2,
                      "status": "passed",
                      "duration": 35188,
                      "errors": [],
                      "stdout": [],
                      "stderr": [],
                      "retry": 0,
                      "startTime": "2026-07-14T01:48:02.805Z",
                      "annotations": [],
                      "attachments": []
                    }
                  ],
                  "status": "expected"
                }
              ],
              "id": "784c2edf0f252052d463-88eba90cfc294d6d0ad1",
              "file": "falabella_playwright.spec.ts",
              "line": 52,
              "column": 7
            },
            {
              "title": "TC-04: Filtros de Ordenamiento - Reestructuración de catálogo de menor a mayor",
              "ok": true,
              "tags": [],
              "tests": [
                {
                  "timeout": 30000,
                  "annotations": [],
                  "expectedStatus": "passed",
                  "projectId": "chromium",
                  "projectName": "chromium",
                  "results": [
                    {
                      "workerIndex": 3,
                      "parallelIndex": 3,
                      "status": "timedOut",
                      "duration": 35390,
                      "error": {
                        "message": "\u001b[31mTest timeout of 30000ms exceeded.\u001b[39m",
                        "stack": "\u001b[31mTest timeout of 30000ms exceeded.\u001b[39m"
                      },
                      "errors": [
                        {
                          "message": "\u001b[31mTest timeout of 30000ms exceeded.\u001b[39m"
                        }
                      ],
                      "stdout": [],
                      "stderr": [],
                      "retry": 0,
                      "startTime": "2026-07-14T01:48:02.747Z",
                      "annotations": [],
                      "attachments": [
                        {
                          "name": "screenshot",
                          "contentType": "image/png",
                          "path": "D:\\falabella\\test-results\\falabella_playwright-Suite-7fcd3-e-catálogo-de-menor-a-mayor-chromium\\test-failed-1.png"
                        },
                        {
                          "name": "video",
                          "contentType": "video/webm",
                          "path": "D:\\falabella\\test-results\\falabella_playwright-Suite-7fcd3-e-catálogo-de-menor-a-mayor-chromium\\video.webm"
                        },
                        {
                          "name": "error-context",
                          "contentType": "text/markdown",
                          "path": "D:\\falabella\\test-results\\falabella_playwright-Suite-7fcd3-e-catálogo-de-menor-a-mayor-chromium\\error-context.md"
                        }
                      ]
                    },
                    {
                      "workerIndex": 5,
                      "parallelIndex": 3,
                      "status": "passed",
                      "duration": 42636,
                      "errors": [],
                      "stdout": [],
                      "stderr": [],
                      "retry": 1,
                      "startTime": "2026-07-14T01:48:49.039Z",
                      "annotations": [],
                      "attachments": [
                        {
                          "name": "trace",
                          "contentType": "application/zip",
                          "path": "D:\\falabella\\test-results\\falabella_playwright-Suite-7fcd3-e-catálogo-de-menor-a-mayor-chromium-retry1\\trace.zip"
                        }
                      ]
                    }
                  ],
                  "status": "flaky"
                }
              ],
              "id": "784c2edf0f252052d463-6f099808f9dd8fa17f1f",
              "file": "falabella_playwright.spec.ts",
              "line": 82,
              "column": 7
            },
            {
              "title": "TC-05: Búsqueda sin Coincidencias",
              "ok": true,
              "tags": [],
              "tests": [
                {
                  "timeout": 30000,
                  "annotations": [],
                  "expectedStatus": "passed",
                  "projectId": "chromium",
                  "projectName": "chromium",
                  "results": [
                    {
                      "workerIndex": 1,
                      "parallelIndex": 1,
                      "status": "passed",
                      "duration": 27404,
                      "errors": [],
                      "stdout": [],
                      "stderr": [],
                      "retry": 0,
                      "startTime": "2026-07-14T01:48:22.780Z",
                      "annotations": [],
                      "attachments": []
                    }
                  ],
                  "status": "expected"
                }
              ],
              "id": "784c2edf0f252052d463-aeff6a4b9481f281a055",
              "file": "falabella_playwright.spec.ts",
              "line": 99,
              "column": 7
            },
            {
              "title": "TC-06: Carrito - Adición exitosa de un artículo estándar (Nintendo Switch)",
              "ok": true,
              "tags": [],
              "tests": [
                {
                  "timeout": 30000,
                  "annotations": [],
                  "expectedStatus": "passed",
                  "projectId": "chromium",
                  "projectName": "chromium",
                  "results": [
                    {
                      "workerIndex": 2,
                      "parallelIndex": 2,
                      "status": "timedOut",
                      "duration": 43270,
                      "error": {
                        "message": "\u001b[31mTest timeout of 30000ms exceeded.\u001b[39m",
                        "stack": "\u001b[31mTest timeout of 30000ms exceeded.\u001b[39m"
                      },
                      "errors": [
                        {
                          "message": "\u001b[31mTest timeout of 30000ms exceeded.\u001b[39m"
                        }
                      ],
                      "stdout": [],
                      "stderr": [],
                      "retry": 0,
                      "startTime": "2026-07-14T01:48:41.193Z",
                      "annotations": [],
                      "attachments": [
                        {
                          "name": "screenshot",
                          "contentType": "image/png",
                          "path": "D:\\falabella\\test-results\\falabella_playwright-Suite-63b58-o-estándar-Nintendo-Switch--chromium\\test-failed-1.png"
                        },
                        {
                          "name": "video",
                          "contentType": "video/webm",
                          "path": "D:\\falabella\\test-results\\falabella_playwright-Suite-63b58-o-estándar-Nintendo-Switch--chromium\\video.webm"
                        },
                        {
                          "name": "error-context",
                          "contentType": "text/markdown",
                          "path": "D:\\falabella\\test-results\\falabella_playwright-Suite-63b58-o-estándar-Nintendo-Switch--chromium\\error-context.md"
                        }
                      ]
                    },
                    {
                      "workerIndex": 7,
                      "parallelIndex": 2,
                      "status": "passed",
                      "duration": 34806,
                      "errors": [],
                      "stdout": [],
                      "stderr": [],
                      "retry": 1,
                      "startTime": "2026-07-14T01:49:37.372Z",
                      "annotations": [],
                      "attachments": [
                        {
                          "name": "trace",
                          "contentType": "application/zip",
                          "path": "D:\\falabella\\test-results\\falabella_playwright-Suite-63b58-o-estándar-Nintendo-Switch--chromium-retry1\\trace.zip"
                        }
                      ]
                    }
                  ],
                  "status": "flaky"
                }
              ],
              "id": "784c2edf0f252052d463-9f04cce002c0da40639d",
              "file": "falabella_playwright.spec.ts",
              "line": 129,
              "column": 7
            },
            {
              "title": "TC-07: Carrito - Flujo de variantes de indumentaria (Tallas S y M)",
              "ok": true,
              "tags": [],
              "tests": [
                {
                  "timeout": 30000,
                  "annotations": [],
                  "expectedStatus": "passed",
                  "projectId": "chromium",
                  "projectName": "chromium",
                  "results": [
                    {
                      "workerIndex": 1,
                      "parallelIndex": 1,
                      "status": "timedOut",
                      "duration": 36779,
                      "error": {
                        "message": "\u001b[31mTest timeout of 30000ms exceeded.\u001b[39m",
                        "stack": "\u001b[31mTest timeout of 30000ms exceeded.\u001b[39m"
                      },
                      "errors": [
                        {
                          "message": "\u001b[31mTest timeout of 30000ms exceeded.\u001b[39m"
                        },
                        {
                          "location": {
                            "file": "D:\\falabella\\tests\\e2e\\falabella_playwright.spec.ts",
                            "column": 16,
                            "line": 142
                          },
                          "message": "Error: page.goto: Test timeout of 30000ms exceeded.\nCall log:\n\u001b[2m  - navigating to \"https://www.falabella.com.pe/falabella-pe/product/149591161/Casaca-Denim-Premium-Element%C2%AE-Corte-Moderno-Botones-Inoxidables-y-Tela-100-Durable/149591177\", waiting until \"load\"\u001b[22m\n\n\n\u001b[0m \u001b[90m 140 |\u001b[39m\n \u001b[90m 141 |\u001b[39m   test(\u001b[32m'TC-07: Carrito - Flujo de variantes de indumentaria (Tallas S y M)'\u001b[39m\u001b[33m,\u001b[39m \u001b[36masync\u001b[39m ({ page }) \u001b[33m=>\u001b[39m {\n\u001b[31m\u001b[1m>\u001b[22m\u001b[39m\u001b[90m 142 |\u001b[39m     \u001b[36mawait\u001b[39m page\u001b[33m.\u001b[39mgoto(\u001b[32m'https://www.falabella.com.pe/falabella-pe/product/149591161/Casaca-Denim-Premium-Element%C2%AE-Corte-Moderno-Botones-Inoxidables-y-Tela-100-Durable/149591177'\u001b[39m)\u001b[33m;\u001b[39m\n \u001b[90m     |\u001b[39m                \u001b[31m\u001b[1m^\u001b[22m\u001b[39m\n \u001b[90m 143 |\u001b[39m     \u001b[36mconst\u001b[39m btnOpciones \u001b[33m=\u001b[39m page\u001b[33m.\u001b[39mlocator(\u001b[32m'button:has-text(\"Elige tus opciones\")'\u001b[39m)\u001b[33m.\u001b[39mfirst()\u001b[33m;\u001b[39m\n \u001b[90m 144 |\u001b[39m     \u001b[36mawait\u001b[39m btnOpciones\u001b[33m.\u001b[39mwaitFor({ state\u001b[33m:\u001b[39m \u001b[32m'visible'\u001b[39m\u001b[33m,\u001b[39m timeout\u001b[33m:\u001b[39m \u001b[35m10000\u001b[39m })\u001b[33m;\u001b[39m\n \u001b[90m 145 |\u001b[39m     \u001b[36mawait\u001b[39m btnOpciones\u001b[33m.\u001b[39mclick()\u001b[33m;\u001b[39m\u001b[0m\n\u001b[2m    at D:\\falabella\\tests\\e2e\\falabella_playwright.spec.ts:142:16\u001b[22m"
                        }
                      ],
                      "stdout": [],
                      "stderr": [],
                      "retry": 0,
                      "startTime": "2026-07-14T01:48:50.296Z",
                      "annotations": [],
                      "attachments": [
                        {
                          "name": "screenshot",
                          "contentType": "image/png",
                          "path": "D:\\falabella\\test-results\\falabella_playwright-Suite-72246--indumentaria-Tallas-S-y-M--chromium\\test-failed-1.png"
                        },
                        {
                          "name": "video",
                          "contentType": "video/webm",
                          "path": "D:\\falabella\\test-results\\falabella_playwright-Suite-72246--indumentaria-Tallas-S-y-M--chromium\\video.webm"
                        },
                        {
                          "name": "error-context",
                          "contentType": "text/markdown",
                          "path": "D:\\falabella\\test-results\\falabella_playwright-Suite-72246--indumentaria-Tallas-S-y-M--chromium\\error-context.md"
                        }
                      ]
                    },
                    {
                      "workerIndex": 6,
                      "parallelIndex": 1,
                      "status": "passed",
                      "duration": 35411,
                      "errors": [],
                      "stdout": [],
                      "stderr": [],
                      "retry": 1,
                      "startTime": "2026-07-14T01:49:37.549Z",
                      "annotations": [],
                      "attachments": [
                        {
                          "name": "trace",
                          "contentType": "application/zip",
                          "path": "D:\\falabella\\test-results\\falabella_playwright-Suite-72246--indumentaria-Tallas-S-y-M--chromium-retry1\\trace.zip"
                        }
                      ]
                    }
                  ],
                  "status": "flaky"
                }
              ],
              "id": "784c2edf0f252052d463-838c24c7bef1df39e8c2",
              "file": "falabella_playwright.spec.ts",
              "line": 141,
              "column": 7
            },
            {
              "title": "TC-08: Carrito - Incremento de cantidades de producto vía TestID",
              "ok": true,
              "tags": [],
              "tests": [
                {
                  "timeout": 30000,
                  "annotations": [],
                  "expectedStatus": "passed",
                  "projectId": "chromium",
                  "projectName": "chromium",
                  "results": [
                    {
                      "workerIndex": 5,
                      "parallelIndex": 3,
                      "status": "passed",
                      "duration": 6308,
                      "errors": [],
                      "stdout": [],
                      "stderr": [],
                      "retry": 0,
                      "startTime": "2026-07-14T01:49:34.363Z",
                      "annotations": [],
                      "attachments": []
                    }
                  ],
                  "status": "expected"
                }
              ],
              "id": "784c2edf0f252052d463-ed786c9b3dd2877c42d9",
              "file": "falabella_playwright.spec.ts",
              "line": 156,
              "column": 7
            },
            {
              "title": "TC-09: Carrito - Eliminación completa de un ítem del resumen de orden",
              "ok": true,
              "tags": [],
              "tests": [
                {
                  "timeout": 30000,
                  "annotations": [],
                  "expectedStatus": "passed",
                  "projectId": "chromium",
                  "projectName": "chromium",
                  "results": [
                    {
                      "workerIndex": 5,
                      "parallelIndex": 3,
                      "status": "passed",
                      "duration": 17877,
                      "errors": [],
                      "stdout": [],
                      "stderr": [],
                      "retry": 0,
                      "startTime": "2026-07-14T01:49:40.766Z",
                      "annotations": [],
                      "attachments": []
                    }
                  ],
                  "status": "expected"
                }
              ],
              "id": "784c2edf0f252052d463-88101c125a9be4978160",
              "file": "falabella_playwright.spec.ts",
              "line": 180,
              "column": 7
            },
            {
              "title": "TC-10: Carrito - Decremento controlado de cantidades mínimas",
              "ok": true,
              "tags": [],
              "tests": [
                {
                  "timeout": 30000,
                  "annotations": [],
                  "expectedStatus": "passed",
                  "projectId": "chromium",
                  "projectName": "chromium",
                  "results": [
                    {
                      "workerIndex": 8,
                      "parallelIndex": 0,
                      "status": "passed",
                      "duration": 12458,
                      "errors": [],
                      "stdout": [],
                      "stderr": [],
                      "retry": 0,
                      "startTime": "2026-07-14T01:49:48.099Z",
                      "annotations": [],
                      "attachments": []
                    }
                  ],
                  "status": "expected"
                }
              ],
              "id": "784c2edf0f252052d463-413f2426e9eadfcd560d",
              "file": "falabella_playwright.spec.ts",
              "line": 192,
              "column": 7
            }
          ]
        }
      ]
    }
  ],
  "errors": [],
  "stats": {
    "startTime": "2026-07-14T01:48:01.624Z",
    "duration": 134092.359,
    "expected": 6,
    "skipped": 0,
    "unexpected": 1,
    "flaky": 3
  }
}